Computer Architecture and Design/Lab 6/HalfAdd.v
module NAND(Y,A,B);
    output wire Y;
    input wire A,B;
    wire Yd;
    and and1(Yd,A,B);
    not not1(Y,Yd);
endmodule
module HalfAdd ( Cout , Sum , A, B ) ;
  input A, B ;
  output Cout , Sum ;
   
    /*declare internal nets */
    wire ABnot;
    wire ABnotB;
    wire ABnotA; 
    /*instantiate gate level modules*/
    NAND nand0(ABnot,A,B); //1st level nand for S and C
    NAND  nand11S(ABnotA,A,ABnot); //2nd level nand for S
    NAND nand12S (ABnotB,B,ABnot); //2nd level nand for S
    NAND nand2S (Sum, ABnotB,ABnotA); //3rd level nand for S
    NAND nand1C(Cout,ABnot,ABnot); // 2nd level nand for C


endmodule //designate end of module

Computer Architecture and Design/Lab 6/HalfAddTest.v
`timescale 1ns / 1ps

////////////////////////////////////////////////////////////////////////////////
// Company: 
// Engineer:
//
// Create Date:   15:12:10 03/02/2009
// Design Name:   HalfAdd
// Module Name:   E:/350/Lab6/HalfAdd/HalfAddTest.v
// Project Name:  HalfAdd
// Target Device:  
// Tool versions:  
// Description: 
//
// Verilog Test Fixture created by ISE for module: HalfAdd
//
// Dependencies:
// 
// Revision:
// Revision 0.01 - File Created
// Additional Comments:
// 
////////////////////////////////////////////////////////////////////////////////

`define STRLEN 15
module HalfAddTest_v;

   task passTest;
      input [1:0] actualOut, expectedOut;
      input [`STRLEN*8:0] testType;
      inout [7:0]         passed;
      
      if(actualOut == expectedOut) begin $display ("%s passed", testType); passed = passed + 1; end
      else $display ("%s failed: %d should be %d", testType, actualOut, expectedOut);
   endtask
   
   task allPassed;
      input [7:0] passed;
      input [7:0] numTests;
      
      if(passed == numTests) $display ("All tests passed");
      else $display("Some tests failed");
   endtask

   // Inputs
   reg            A;
   reg            B;
   reg [7:0]      passed;

   // Outputs
   wire           Cout;
   wire           Sum;

   initial //This initial block used to dump all wire/reg values to dump file
     begin
       $dumpfile("HalfAddTest.vcd");
       $dumpvars(0,HalfAddTest_v);
     end

   // Instantiate the Device Under Test (DUT)
   HalfAdd dut (
		.Cout(Cout), 
		.Sum(Sum), 
		.A(A), 
		.B(B)
	        );

   initial begin
      // Initialize Inputs
      A = 0;
      B = 0;
      passed = 0;

      // Add stimulus here
      #90; A=0;B=0; #10; passTest({Cout, Sum}, 0, "0+0", passed);
      #90; A=0;B=1; #10; passTest({Cout, Sum}, 1, "0+1", passed);
      #90; A=1;B=0; #10; passTest({Cout, Sum}, 1, "1+0", passed);
      #90; A=1;B=1; #10; passTest({Cout, Sum}, 2, "1+1", passed);
	  #90;
      
      allPassed(passed, 4);

   end
   
endmodule

Computer Architecture and Design/Lab 6/HalfAddTest.vcd
$date
	Wed Mar 24 02:53:56 2021
$end
$version
	Icarus Verilog
$end
$timescale
	1ps
$end
$scope module HalfAddTest_v $end
$var wire 1 ! Sum $end
$var wire 1 " Cout $end
$var reg 1 # A $end
$var reg 1 $ B $end
$var reg 8 % passed [7:0] $end
$scope module dut $end
$var wire 1 # A $end
$var wire 1 $ B $end
$var wire 1 ! Sum $end
$var wire 1 " Cout $end
$var wire 1 & ABnotB $end
$var wire 1 ' ABnotA $end
$var wire 1 ( ABnot $end
$scope module nand0 $end
$var wire 1 # A $end
$var wire 1 $ B $end
$var wire 1 ( Y $end
$var wire 1 ) Yd $end
$upscope $end
$scope module nand11S $end
$var wire 1 # A $end
$var wire 1 ( B $end
$var wire 1 ' Y $end
$var wire 1 * Yd $end
$upscope $end
$scope module nand12S $end
$var wire 1 $ A $end
$var wire 1 ( B $end
$var wire 1 & Y $end
$var wire 1 + Yd $end
$upscope $end
$scope module nand1C $end
$var wire 1 ( A $end
$var wire 1 ( B $end
$var wire 1 " Y $end
$var wire 1 , Yd $end
$upscope $end
$scope module nand2S $end
$var wire 1 & A $end
$var wire 1 ' B $end
$var wire 1 ! Y $end
$var wire 1 - Yd $end
$upscope $end
$upscope $end
$scope task allPassed $end
$var reg 8 . numTests [7:0] $end
$var reg 8 / passed [7:0] $end
$upscope $end
$scope task passTest $end
$var reg 2 0 actualOut [1:0] $end
$var reg 2 1 expectedOut [1:0] $end
$var reg 8 2 passed [7:0] $end
$var reg 121 3 testType [120:0] $end
$upscope $end
$upscope $end
$enddefinitions $end
#0
$dumpvars
bx 3
bx 2
bx 1
bx 0
bx /
bx .
1-
1,
0+
0*
0)
1(
1'
1&
b0 %
0$
0#
0"
0!
$end
#100000
b1 %
b1 2
b1100000010101100110000 3
b0 1
b0 0
#190000
1!
0-
0&
1+
1$
#200000
b10 %
b10 2
b1100000010101100110001 3
b1 1
b1 0
#290000
1&
0'
0+
1*
0$
1#
#300000
b11 %
b11 2
b1100010010101100110000 3
#390000
0!
1-
1'
1"
0*
0,
0(
1&
1)
0+
1$
#400000
b100 %
b100 2
b1100010010101100110001 3
b10 1
b10 0
#490000
b100 .
b100 /
