Computer Architecture and Design/Lab 7/registerfile/RegisterFile.v
module RegisterFile(BusA, BusB, BusW,RA, RB, RW, RegWr, Clk);
    output wire [63:0] BusA;
    output wire  [63:0] BusB;
    input wire [63:0] BusW;
    input wire [4:0] RA;
    input wire [4:0] RB;
    input wire [4:0] RW;
    input wire RegWr;
    input wire Clk;
    reg [63:0] registers [31:0];
    
    //assign
    //X31 always needs to be XZR so it sets itself to zero at Clk (for the
    //beginning) and whenever it is changed. 
    always @ (Clk or registers[31]) begin 
        registers[31] <= 64'd0; 
    end
    //BusA and BusB assigned immediately
       assign  #2 BusA = registers[RA];
       assign  #2 BusB = registers[RB];
    //end
     
    //register write only happens on negedge when RegWr is 1
    always @ (negedge Clk) begin
        if(RegWr)
            registers[RW] <= #3 BusW;
    end
endmodule

Computer Architecture and Design/Lab 7/MyFileRegisterTest.v
`timescale 1ns / 1ps
////////////////////////////////////////////////////////////////////////////////
// Company: 
// Engineer:
//
// Create Date:   10:13:28 03/03/2009
// Design Name:   RegisterFile
// Module Name:   E:/350/Lab7/RegisterFile/RegisterFileTest.v
// Project Name:  RegisterFile
// Target Device:  
// Tool versions:  
// Description: 
//
// Verilog Test Fixture created by ISE for module: RegisterFile
//
// Dependencies:
// 
// Revision:
// Revision 0.01 - File Created
// Additional Comments:
// 
////////////////////////////////////////////////////////////////////////////////

`define STRLEN 32
module MyRegisterFileTest_v;


	task passTest;
		input [63:0] actualOut, expectedOut;
		input [`STRLEN*8:0] testType;
		inout [7:0] passed;
	
		if(actualOut == expectedOut) begin $display ("%s %d passed", testType, actualOut); passed = passed + 1; end
		else $display ("%s failed: %d should be %d", testType, actualOut, expectedOut);
	endtask
	
	task allPassed;
		input [7:0] passed;
		input [7:0] numTests;
		
		if(passed == numTests) $display ("All tests passed");
		else $display("Some tests failed");
	endtask

	// Inputs
	reg [63:0] BusW;
	reg [4:0] RA;
	reg [4:0] RB;
	reg [4:0] RW;
	reg RegWr;
	reg Clk;
	reg [7:0] passed;
	reg [4:0] i;
	reg [4:0] a;
	reg [63:0] i64;

	// Outputs
	wire [63:0] BusA;
	wire [63:0] BusB;

	// Instantiate the Unit Under Test (UUT)
	RegisterFile uut (
		.BusA(BusA), 
		.BusB(BusB), 
		.BusW(BusW), 
		.RA(RA), 
		.RB(RB), 
		.RW(RW), 
		.RegWr(RegWr), 
		.Clk(Clk)
	);
	
	initial //This initial block used to dump all wire/reg values to dump file
         begin
           $dumpfile("MyRegisterFileTest.vcd");
           $dumpvars(0,MyRegisterFileTest_v);
         end

	initial begin
		// Initialize Inputs
		BusW = 0;
		RA = 0;
		RB = 0;
		RW = 0;
		RegWr = 0;
		Clk = 1;
		passed = 0;
		i = 0;
		a = 5;
		i64 = 0;
		
		
		#10;
		//for loop to change every value in registerfile to its
		//register address/index
		for (i = 0; i < 31; i = i +1) begin
            a <= a + 1; // executes this code 16 times
           
            i64 = {59'b0,i}; //needed to change 5 bit i to 64 bit i so it can be used as BusW
             //$display("%d",i64);
            {RA, RB, RW, BusW, RegWr} = {i, 5'd0, i, i64, 1'b1};
            Clk = 0;
            #10;
            Clk = 1;
            //passTest(BusA, i, "Initial Check", passed);
            
        end
        Clk = 1;
        {RA, RB, RW, RegWr, BusW} = {5'h0, 5'h1, 5'h0, 1'b0,64'h0};
		#4;
		passTest(BusA, 64'h0, "0 Initial Value Check A, Currently", passed);
		passTest(BusB, 64'h1, "Initial Value Check B, Currently", passed);
		#6; Clk = 0; #10; Clk = 1; //negedge happens when Clk goes from 1 to 0
		passTest(BusA, 64'h0, "After Write A, Currently", passed);
		passTest(BusB, 64'h1, "After Write B, Currently", passed);
		
		{RA, RB, RW, RegWr, BusW} = {5'h2, 5'h3, 5'h1, 1'b0,64'h1000};
		#4;
		passTest(BusA, 64'h2, " 1 Initial Value Check A, Currently", passed);
		passTest(BusB, 64'h3, "Initial Value Check B, Currently", passed);
		#6; Clk = 0; #10; Clk = 1;
		passTest(BusA, 64'h2, "After Write A, Currently", passed);
		passTest(BusB, 64'h3, "After Write B, Currently", passed);
		
		{RA, RB, RW, RegWr, BusW} = {5'h4, 5'h5, 5'h0, 1'b1,64'h1000};
		#4;
		passTest(BusA, 64'h4, "2 Initial Value Check A, Currently", passed);
		passTest(BusB, 64'h5, "Initial Value Check B, Currently", passed);
		#6; Clk = 0; #10; Clk = 1;
		passTest(BusA, 64'h4, "After Write A, Currently", passed);
		passTest(BusB, 64'h5, "After Write B, Currently", passed);
		
		
		{RA, RB, RW, RegWr, BusW} = {5'h6, 5'h7, 5'hA, 1'b1,64'h1010};
		#4;
		passTest(BusA, 64'h6, "3 Initial Value Check A, Currently", passed);
		passTest(BusB, 64'h7, "Initial Value Check B, Currently", passed);
		#6; Clk = 0; #10; Clk = 1;
		passTest(BusA, 64'h6, "After Write A, Currently", passed);
		passTest(BusB, 64'h7, "After Write B, Currently", passed);
		
		{RA, RB, RW, RegWr, BusW} = {5'h8, 5'h9, 5'hB, 1'b1,64'h103000};
		#4;
		passTest(BusA, 64'h8, "4 Initial Value Check A, Currently", passed);
		passTest(BusB, 64'h9, "Initial Value Check B, Currently", passed);
		#6; Clk = 0; #10; Clk = 1;
		passTest(BusA, 64'h8, "After Write A, Currently", passed);
		passTest(BusB, 64'h9, "After Write B, Currently", passed);
		
		{RA, RB, RW, RegWr, BusW} = {5'hA, 5'hB, 5'hC, 1'b0,64'h0};
		#4;
		passTest(BusA, 64'h1010, "5 Initial Value Check A, Currently", passed);
		passTest(BusB, 64'h103000, "Initial Value Check B, Currently", passed);
		#6; Clk = 0; #10; Clk = 1;
		passTest(BusA, 64'h1010, "After Write A, Currently", passed);
		passTest(BusB, 64'h103000, "After Write B, Currently", passed);
		
		{RA, RB, RW, RegWr, BusW} = {5'hC, 5'hD, 5'hD, 1'b1,64'hABCD};
		#4;
		passTest(BusA, 64'hC, "6 Initial Value Check A, Currently", passed);
		passTest(BusB, 64'hD, "Initial Value Check B, Currently", passed);
		#6; Clk = 0; #10; Clk = 1;
		passTest(BusA, 64'hC, "After Write A, Currently", passed);
		passTest(BusB, 64'hABCD, "After Write B, Currently", passed);
		
		{RA, RB, RW, RegWr, BusW} = {5'hE, 5'hF, 5'hE, 1'b0,64'h9080009};
		#4;
		passTest(BusA, 64'hE, "7 Initial Value Check A, Currently", passed);
		passTest(BusB, 64'hF, "Initial Value Check B, Currently", passed);
		#6; Clk = 0; #10; Clk = 1;
		passTest(BusA, 64'hE, "After Write A, Currently", passed);
		passTest(BusB, 64'hF, "After Write B, Currently", passed);
        
        
		end
endmodule

Computer Architecture and Design/Lab 7/MyRegisterFileTest.vcd
$date
	Thu Apr 15 23:49:13 2021
$end
$version
	Icarus Verilog
$end
$timescale
	1ps
$end
$scope module MyRegisterFileTest_v $end
$var wire 64 ! BusB [63:0] $end
$var wire 64 " BusA [63:0] $end
$var reg 64 # BusW [63:0] $end
$var reg 1 $ Clk $end
$var reg 5 % RA [4:0] $end
$var reg 5 & RB [4:0] $end
$var reg 5 ' RW [4:0] $end
$var reg 1 ( RegWr $end
$var reg 5 ) a [4:0] $end
$var reg 5 * i [4:0] $end
$var reg 64 + i64 [63:0] $end
$var reg 8 , passed [7:0] $end
$scope module uut $end
$var wire 64 - BusA [63:0] $end
$var wire 64 . BusB [63:0] $end
$var wire 64 / BusW [63:0] $end
$var wire 1 $ Clk $end
$var wire 5 0 RA [4:0] $end
$var wire 5 1 RB [4:0] $end
$var wire 5 2 RW [4:0] $end
$var wire 1 ( RegWr $end
$upscope $end
$scope task allPassed $end
$var reg 8 3 numTests [7:0] $end
$var reg 8 4 passed [7:0] $end
$upscope $end
$scope task passTest $end
$var reg 64 5 actualOut [63:0] $end
$var reg 64 6 expectedOut [63:0] $end
$var reg 8 7 passed [7:0] $end
$var reg 257 8 testType [256:0] $end
$upscope $end
$upscope $end
$enddefinitions $end
#0
$dumpvars
bx 8
bx 7
bx 6
bx 5
bx 4
bx 3
b0 2
b0 1
b0 0
b0 /
bx .
bx -
b0 ,
b0 +
b0 *
b101 )
0(
b0 '
b0 &
b0 %
1$
b0 #
bx "
bx !
$end
#10000
b110 )
0$
1(
#15000
b0 "
b0 -
b0 !
b0 .
#20000
b111 )
b1 %
b1 0
b1 '
b1 2
b1 #
b1 /
b1 +
b1 *
0$
#22000
bx "
bx -
#25000
b1 "
b1 -
#30000
b1000 )
b10 %
b10 0
b10 '
b10 2
b10 #
b10 /
b10 +
b10 *
0$
#32000
bx "
bx -
#35000
b10 "
b10 -
#40000
b1001 )
b11 %
b11 0
b11 '
b11 2
b11 #
b11 /
b11 +
b11 *
0$
#42000
bx "
bx -
#45000
b11 "
b11 -
#50000
b1010 )
b100 %
b100 0
b100 '
b100 2
b100 #
b100 /
b100 +
b100 *
0$
#52000
bx "
bx -
#55000
b100 "
b100 -
#60000
b1011 )
b101 %
b101 0
b101 '
b101 2
b101 #
b101 /
b101 +
b101 *
0$
#62000
bx "
bx -
#65000
b101 "
b101 -
#70000
b1100 )
b110 %
b110 0
b110 '
b110 2
b110 #
b110 /
b110 +
b110 *
0$
#72000
bx "
bx -
#75000
b110 "
b110 -
#80000
b1101 )
b111 %
b111 0
b111 '
b111 2
b111 #
b111 /
b111 +
b111 *
0$
#82000
bx "
bx -
#85000
b111 "
b111 -
#90000
b1110 )
b1000 %
b1000 0
b1000 '
b1000 2
b1000 #
b1000 /
b1000 +
b1000 *
0$
#92000
bx "
bx -
#95000
b1000 "
b1000 -
#100000
b1111 )
b1001 %
b1001 0
b1001 '
b1001 2
b1001 #
b1001 /
b1001 +
b1001 *
0$
#102000
bx "
bx -
#105000
b1001 "
b1001 -
#110000
b10000 )
b1010 %
b1010 0
b1010 '
b1010 2
b1010 #
b1010 /
b1010 +
b1010 *
0$
#112000
bx "
bx -
#115000
b1010 "
b1010 -
#120000
b10001 )
b1011 %
b1011 0
b1011 '
b1011 2
b1011 #
b1011 /
b1011 +
b1011 *
0$
#122000
bx "
bx -
#125000
b1011 "
b1011 -
#130000
b10010 )
b1100 %
b1100 0
b1100 '
b1100 2
b1100 #
b1100 /
b1100 +
b1100 *
0$
#132000
bx "
bx -
#135000
b1100 "
b1100 -
#140000
b10011 )
b1101 %
b1101 0
b1101 '
b1101 2
b1101 #
b1101 /
b1101 +
b1101 *
0$
#142000
bx "
bx -
#145000
b1101 "
b1101 -
#150000
b10100 )
b1110 %
b1110 0
b1110 '
b1110 2
b1110 #
b1110 /
b1110 +
b1110 *
0$
#152000
bx "
bx -
#155000
b1110 "
b1110 -
#160000
b10101 )
b1111 %
b1111 0
b1111 '
b1111 2
b1111 #
b1111 /
b1111 +
b1111 *
0$
#162000
bx "
bx -
#165000
b1111 "
b1111 -
#170000
b10110 )
b10000 %
b10000 0
b10000 '
b10000 2
b10000 #
b10000 /
b10000 +
b10000 *
0$
#172000
bx "
bx -
#175000
b10000 "
b10000 -
#180000
b10111 )
b10001 %
b10001 0
b10001 '
b10001 2
b10001 #
b10001 /
b10001 +
b10001 *
0$
#182000
bx "
bx -
#185000
b10001 "
b10001 -
#190000
b11000 )
b10010 %
b10010 0
b10010 '
b10010 2
b10010 #
b10010 /
b10010 +
b10010 *
0$
#192000
bx "
bx -
#195000
b10010 "
b10010 -
#200000
b11001 )
b10011 %
b10011 0
b10011 '
b10011 2
b10011 #
b10011 /
b10011 +
b10011 *
0$
#202000
bx "
bx -
#205000
b10011 "
b10011 -
#210000
b11010 )
b10100 %
b10100 0
b10100 '
b10100 2
b10100 #
b10100 /
b10100 +
b10100 *
0$
#212000
bx "
bx -
#215000
b10100 "
b10100 -
#220000
b11011 )
b10101 %
b10101 0
b10101 '
b10101 2
b10101 #
b10101 /
b10101 +
b10101 *
0$
#222000
bx "
bx -
#225000
b10101 "
b10101 -
#230000
b11100 )
b10110 %
b10110 0
b10110 '
b10110 2
b10110 #
b10110 /
b10110 +
b10110 *
0$
#232000
bx "
bx -
#235000
b10110 "
b10110 -
#240000
b11101 )
b10111 %
b10111 0
b10111 '
b10111 2
b10111 #
b10111 /
b10111 +
b10111 *
0$
#242000
bx "
bx -
#245000
b10111 "
b10111 -
#250000
b11110 )
b11000 %
b11000 0
b11000 '
b11000 2
b11000 #
b11000 /
b11000 +
b11000 *
0$
#252000
bx "
bx -
#255000
b11000 "
b11000 -
#260000
b11111 )
b11001 %
b11001 0
b11001 '
b11001 2
b11001 #
b11001 /
b11001 +
b11001 *
0$
#262000
bx "
bx -
#265000
b11001 "
b11001 -
#270000
b0 )
b11010 %
b11010 0
b11010 '
b11010 2
b11010 #
b11010 /
b11010 +
b11010 *
0$
#272000
bx "
bx -
#275000
b11010 "
b11010 -
#280000
b1 )
b11011 %
b11011 0
b11011 '
b11011 2
b11011 #
b11011 /
b11011 +
b11011 *
0$
#282000
bx "
bx -
#285000
b11011 "
b11011 -
#290000
b10 )
b11100 %
b11100 0
b11100 '
b11100 2
b11100 #
b11100 /
b11100 +
b11100 *
0$
#292000
bx "
bx -
#295000
b11100 "
b11100 -
#300000
b11 )
b11101 %
b11101 0
b11101 '
b11101 2
b11101 #
b11101 /
b11101 +
b11101 *
0$
#302000
bx "
bx -
#305000
b11101 "
b11101 -
#310000
b100 )
b11110 %
b11110 0
b11110 '
b11110 2
b11110 #
b11110 /
b11110 +
b11110 *
0$
#312000
bx "
bx -
#315000
b11110 "
b11110 -
#320000
b0 %
b0 0
b1 &
b1 1
b0 '
b0 2
0(
b0 #
b0 /
b11111 *
1$
#322000
b0 "
b0 -
b1 !
b1 .
#324000
b10 ,
b10 7
b100100101101110011010010111010001101001011000010110110000100000010101100110000101101100011101010110010100100000010000110110100001100101011000110110101100100000010000100010110000100000010000110111010101110010011100100110010101101110011101000110110001111001 8
b1 6
b1 5
#330000
0$
#340000
b10 %
b10 0
b11 &
b11 1
b1 '
b1 2
b1000000000000 #
b1000000000000 /
b100 ,
b100 7
b10000010110011001110100011001010111001000100000010101110111001001101001011101000110010100100000010000100010110000100000010000110111010101110010011100100110010101101110011101000110110001111001 8
b1 6
b1 5
1$
#342000
b10 "
b10 -
b11 !
b11 .
#344000
b110 ,
b110 7
b100100101101110011010010111010001101001011000010110110000100000010101100110000101101100011101010110010100100000010000110110100001100101011000110110101100100000010000100010110000100000010000110111010101110010011100100110010101101110011101000110110001111001 8
b11 6
b11 5
#350000
0$
#360000
b100 %
b100 0
b101 &
b101 1
b0 '
b0 2
1(
b1000 ,
b1000 7
b10000010110011001110100011001010111001000100000010101110111001001101001011101000110010100100000010000100010110000100000010000110111010101110010011100100110010101101110011101000110110001111001 8
b11 6
b11 5
1$
#362000
b100 "
b100 -
b101 !
b101 .
#364000
b1010 ,
b1010 7
b100100101101110011010010111010001101001011000010110110000100000010101100110000101101100011101010110010100100000010000110110100001100101011000110110101100100000010000100010110000100000010000110111010101110010011100100110010101101110011101000110110001111001 8
b101 6
b101 5
#370000
0$
#380000
b110 %
b110 0
b111 &
b111 1
b1010 '
b1010 2
b1000000010000 #
b1000000010000 /
b1100 ,
b1100 7
b10000010110011001110100011001010111001000100000010101110111001001101001011101000110010100100000010000100010110000100000010000110111010101110010011100100110010101101110011101000110110001111001 8
b101 6
b101 5
1$
#382000
b110 "
b110 -
b111 !
b111 .
#384000
b1110 ,
b1110 7
b100100101101110011010010111010001101001011000010110110000100000010101100110000101101100011101010110010100100000010000110110100001100101011000110110101100100000010000100010110000100000010000110111010101110010011100100110010101101110011101000110110001111001 8
b111 6
b111 5
#390000
0$
#400000
b1000 %
b1000 0
b1001 &
b1001 1
b1011 '
b1011 2
b100000011000000000000 #
b100000011000000000000 /
b10000 ,
b10000 7
b10000010110011001110100011001010111001000100000010101110111001001101001011101000110010100100000010000100010110000100000010000110111010101110010011100100110010101101110011101000110110001111001 8
b111 6
b111 5
1$
#402000
b1000 "
b1000 -
b1001 !
b1001 .
#404000
b10010 ,
b10010 7
b100100101101110011010010111010001101001011000010110110000100000010101100110000101101100011101010110010100100000010000110110100001100101011000110110101100100000010000100010110000100000010000110111010101110010011100100110010101101110011101000110110001111001 8
b1001 6
b1001 5
#410000
0$
#420000
b1010 %
b1010 0
b1011 &
b1011 1
b1100 '
b1100 2
0(
b0 #
b0 /
b10100 ,
b10100 7
b10000010110011001110100011001010111001000100000010101110111001001101001011101000110010100100000010000100010110000100000010000110111010101110010011100100110010101101110011101000110110001111001 8
b1001 6
b1001 5
1$
#422000
b1000000010000 "
b1000000010000 -
b100000011000000000000 !
b100000011000000000000 .
#424000
b10110 ,
b10110 7
b100100101101110011010010111010001101001011000010110110000100000010101100110000101101100011101010110010100100000010000110110100001100101011000110110101100100000010000100010110000100000010000110111010101110010011100100110010101101110011101000110110001111001 8
b100000011000000000000 6
b100000011000000000000 5
#430000
0$
#440000
b1100 %
b1100 0
b1101 &
b1101 1
b1101 '
b1101 2
1(
b1010101111001101 #
b1010101111001101 /
b11000 ,
b11000 7
b10000010110011001110100011001010111001000100000010101110111001001101001011101000110010100100000010000100010110000100000010000110111010101110010011100100110010101101110011101000110110001111001 8
b100000011000000000000 6
b100000011000000000000 5
1$
#442000
b1100 "
b1100 -
b1101 !
b1101 .
#444000
b11010 ,
b11010 7
b100100101101110011010010111010001101001011000010110110000100000010101100110000101101100011101010110010100100000010000110110100001100101011000110110101100100000010000100010110000100000010000110111010101110010011100100110010101101110011101000110110001111001 8
b1101 6
b1101 5
#450000
0$
#455000
b1010101111001101 !
b1010101111001101 .
#460000
b1110 %
b1110 0
b1111 &
b1111 1
b1110 '
b1110 2
0(
b1001000010000000000000001001 #
b1001000010000000000000001001 /
b11100 ,
b11100 7
b10000010110011001110100011001010111001000100000010101110111001001101001011101000110010100100000010000100010110000100000010000110111010101110010011100100110010101101110011101000110110001111001 8
b1010101111001101 6
b1010101111001101 5
1$
#462000
b1110 "
b1110 -
b1111 !
b1111 .
#464000
b11110 ,
b11110 7
b100100101101110011010010111010001101001011000010110110000100000010101100110000101101100011101010110010100100000010000110110100001100101011000110110101100100000010000100010110000100000010000110111010101110010011100100110010101101110011101000110110001111001 8
b1111 6
b1111 5
#470000
0$
#480000
b100000 ,
b100000 7
b10000010110011001110100011001010111001000100000010101110111001001101001011101000110010100100000010000100010110000100000010000110111010101110010011100100110010101101110011101000110110001111001 8
b1111 6
b1111 5
1$
