Computer Architecture and Design/Lab 7/NextPClogic.v
module NextPClogic(NextPC, CurrentPC, SignExtImm64, Branch, ALUZero, Uncondbranch);
       input wire [63:0] CurrentPC, SignExtImm64;
       input wire Branch, ALUZero, Uncondbranch;
       output reg [63:0] NextPC;
       reg [63:0] ALUResult ;
       reg [63:0] AddFour;
       //reg PostMux;
       reg AndBranchZero;
       reg selector;
       always @(*) begin //everthing in the always loop runs when anything changes
        ALUResult <= #2 SignExtImm64 + CurrentPC; //adds offset to PC
        AddFour <= #1 CurrentPC + 4; //increment pc by 4
        
        AndBranchZero <= Branch & ALUZero; //for CBZ
        selector <= AndBranchZero | Uncondbranch; //if B, then add offset to pc no matter what
        if (selector) //mux logic
            NextPC <= #1 ALUResult;
        else
            NextPC <= #1 AddFour;
      end
      
       /*initial
    begin
        $monitor("currentPC=%d, NextPC = %d, AndBranchZero = %d, ALUResult = %d, AddFour = %d, ALUZero = %d",CurrentPC,NextPC,AndBranchZero,ALUResult, AddFour, ALUZero);
    end*/

endmodule

Computer Architecture and Design/Lab 7/NextPClogic/NextPClogicTest.v
`define STRLEN 32
module NextPClogic_v;
    task passTest;
		input [64:0] actualOut, expectedOut;
		input [`STRLEN*16:0] testType;
		inout [7:0] passed;
	
		if(actualOut == expectedOut) begin $display ("%s passed", testType); passed = passed + 1; end
		else $display ("%s failed: %x should be %x", testType, actualOut, expectedOut);
	endtask
	
	task allPassed;
		input [7:0] passed;
		input [7:0] numTests;
		
		if(passed == numTests) $display ("All tests passed");
		else $display("Some tests failed");
	endtask
	
	reg [63:0]  CurrentPC;
        reg [63:0] SignExtImm64;
        reg Branch;
        reg ALUZero;
        reg Uncondbranch;
        wire [63:0] NextPC;
        reg [7:0] passed;
        
    initial //This initial block used to dump all wire/reg values to dump file
         begin
           $dumpfile("NextPClogic.vcd");
           $dumpvars(0,NextPClogic_v);
         end


     NextPClogic p(NextPC, CurrentPC, SignExtImm64, Branch, ALUZero, Uncondbranch);


    initial begin
        /*a = 1;
        b = 10;
        c = 1;
        d = 1;
        e = 1;
        //f = 1;*/
    
    
    
   
    
    {CurrentPC, SignExtImm64, Branch, ALUZero, Uncondbranch} = {64'd1,64'd10,1'd1,1'd1,1'd1};     #40;     passTest(NextPC, 64'd11, "Test 1 (PC = 1, SE = 10, B = 1, ALUzero = 1, Uncondbranch = 1)", passed);
    {CurrentPC, SignExtImm64, Branch, ALUZero, Uncondbranch} = {64'd1,64'd10,1'd0,1'd1,1'd1};     #40;     passTest(NextPC, 64'd11, " Test 2 (PC = 1, SE = 10, B = 0, ALUzero = 1, Uncondbranch = 1)", passed);
    {CurrentPC, SignExtImm64, Branch, ALUZero, Uncondbranch} = {64'd1,64'd10,1'd0,1'd1,1'd0};     #40;     passTest(NextPC, 64'd5, " Test 3 (PC = 1, SE = 10, B = 0, ALUzero = 1, Uncondbranch = 0)", passed);
    {CurrentPC, SignExtImm64, Branch, ALUZero, Uncondbranch} = {64'd1,64'd10,1'd1,1'd0,1'd0};     #40;     passTest(NextPC, 64'd5, "Test 4 (PC = 1, SE = 10, B = 1, ALUzero = 0, Uncondbranch = 0)", passed);
    {CurrentPC, SignExtImm64, Branch, ALUZero, Uncondbranch} = {64'd1,64'd10,1'd1,1'd0,1'd1};     #40;     passTest(NextPC, 64'd11, "Test 5 (PC = 1, SE = 10, B = 1, ALUzero = 0, Uncondbranch = 1)", passed);
    {CurrentPC, SignExtImm64, Branch, ALUZero, Uncondbranch} = {64'd1,64'd10,1'd0,1'd0,1'd0};     #40;     passTest(NextPC, 64'd5, "Test 6 (PC = 1, SE = 10, B = 0, ALUzero = 0, Uncondbranch = 0)", passed);
    {CurrentPC, SignExtImm64, Branch, ALUZero, Uncondbranch} = {64'd1,64'd10,1'd0,1'd0,1'd1};     #40;     passTest(NextPC, 64'd11, "Test 7 (PC = 1, SE = 10, B = 0, ALUzero = 0, Uncondbranch = 1)", passed);
    {CurrentPC, SignExtImm64, Branch, ALUZero, Uncondbranch} = {64'd1,64'd10,1'd1,1'd1,1'd0};     #40;     passTest(NextPC, 64'd11, "Test 8 (PC = 1, SE = 10, B = 1, ALUzero = 1, Uncondbranch = 0)", passed);
    
    end

     
    
endmodule

Computer Architecture and Design/Lab 7/NextPClogic.vcd
$date
	Thu Apr 15 23:31:23 2021
$end
$version
	Icarus Verilog
$end
$timescale
	1s
$end
$scope module NextPClogic_v $end
$var wire 64 ! NextPC [63:0] $end
$var reg 1 " ALUZero $end
$var reg 1 # Branch $end
$var reg 64 $ CurrentPC [63:0] $end
$var reg 64 % SignExtImm64 [63:0] $end
$var reg 1 & Uncondbranch $end
$var reg 8 ' passed [7:0] $end
$scope module p $end
$var wire 1 " ALUZero $end
$var wire 1 # Branch $end
$var wire 64 ( CurrentPC [63:0] $end
$var wire 64 ) SignExtImm64 [63:0] $end
$var wire 1 & Uncondbranch $end
$var reg 64 * ALUResult [63:0] $end
$var reg 64 + AddFour [63:0] $end
$var reg 1 , AndBranchZero $end
$var reg 64 - NextPC [63:0] $end
$var reg 1 . selector $end
$upscope $end
$scope task allPassed $end
$var reg 8 / numTests [7:0] $end
$var reg 8 0 passed [7:0] $end
$upscope $end
$scope task passTest $end
$var reg 65 1 actualOut [64:0] $end
$var reg 65 2 expectedOut [64:0] $end
$var reg 8 3 passed [7:0] $end
$var reg 513 4 testType [512:0] $end
$upscope $end
$upscope $end
$enddefinitions $end
#0
$dumpvars
bx 4
bx 3
bx 2
bx 1
bx 0
bx /
1.
bx -
1,
bx +
bx *
b1010 )
b1 (
bx '
1&
b1010 %
b1 $
1#
1"
bx !
$end
#1
b101 +
#2
b1011 *
#3
b1011 !
b1011 -
#40
0,
0#
b101010001100101011100110111010000100000001100010010000000101000010100000100001100100000001111010010000000110001001011000010000001010011010001010010000000111101001000000011000100110000001011000010000001000010001000000011110100100000001100010010110000100000010000010100110001010101011110100110010101110010011011110010000000111101001000000011000100101100001000000101010101101110011000110110111101101110011001000110001001110010011000010110111001100011011010000010000000111101001000000011000100101001 4
b1011 2
b1011 1
#80
0.
0&
b1000000101010001100101011100110111010000100000001100100010000000101000010100000100001100100000001111010010000000110001001011000010000001010011010001010010000000111101001000000011000100110000001011000010000001000010001000000011110100100000001100000010110000100000010000010100110001010101011110100110010101110010011011110010000000111101001000000011000100101100001000000101010101101110011000110110111101101110011001000110001001110010011000010110111001100011011010000010000000111101001000000011000100101001 4
#81
b101 !
b101 -
#120
1#
0"
b1000000101010001100101011100110111010000100000001100110010000000101000010100000100001100100000001111010010000000110001001011000010000001010011010001010010000000111101001000000011000100110000001011000010000001000010001000000011110100100000001100000010110000100000010000010100110001010101011110100110010101110010011011110010000000111101001000000011000100101100001000000101010101101110011000110110111101101110011001000110001001110010011000010110111001100011011010000010000000111101001000000011000000101001 4
b101 2
b101 1
#160
1.
1&
b101010001100101011100110111010000100000001101000010000000101000010100000100001100100000001111010010000000110001001011000010000001010011010001010010000000111101001000000011000100110000001011000010000001000010001000000011110100100000001100010010110000100000010000010100110001010101011110100110010101110010011011110010000000111101001000000011000000101100001000000101010101101110011000110110111101101110011001000110001001110010011000010110111001100011011010000010000000111101001000000011000000101001 4
#161
b1011 !
b1011 -
#200
0.
0#
0&
b101010001100101011100110111010000100000001101010010000000101000010100000100001100100000001111010010000000110001001011000010000001010011010001010010000000111101001000000011000100110000001011000010000001000010001000000011110100100000001100010010110000100000010000010100110001010101011110100110010101110010011011110010000000111101001000000011000000101100001000000101010101101110011000110110111101101110011001000110001001110010011000010110111001100011011010000010000000111101001000000011000100101001 4
b1011 2
b1011 1
#201
b101 !
b101 -
#240
1.
1&
b101010001100101011100110111010000100000001101100010000000101000010100000100001100100000001111010010000000110001001011000010000001010011010001010010000000111101001000000011000100110000001011000010000001000010001000000011110100100000001100000010110000100000010000010100110001010101011110100110010101110010011011110010000000111101001000000011000000101100001000000101010101101110011000110110111101101110011001000110001001110010011000010110111001100011011010000010000000111101001000000011000000101001 4
b101 2
b101 1
#241
b1011 !
b1011 -
#280
1.
1,
1#
1"
0&
b101010001100101011100110111010000100000001101110010000000101000010100000100001100100000001111010010000000110001001011000010000001010011010001010010000000111101001000000011000100110000001011000010000001000010001000000011110100100000001100000010110000100000010000010100110001010101011110100110010101110010011011110010000000111101001000000011000000101100001000000101010101101110011000110110111101101110011001000110001001110010011000010110111001100011011010000010000000111101001000000011000100101001 4
b1011 2
b1011 1
#281
b1011 !
b1011 -
#320
b101010001100101011100110111010000100000001110000010000000101000010100000100001100100000001111010010000000110001001011000010000001010011010001010010000000111101001000000011000100110000001011000010000001000010001000000011110100100000001100010010110000100000010000010100110001010101011110100110010101110010011011110010000000111101001000000011000100101100001000000101010101101110011000110110111101101110011001000110001001110010011000010110111001100011011010000010000000111101001000000011000000101001 4
