Computer Architecture and Design/Lab 8/DataMemory.v
`define SIZE 1024
module DataMemory(ReadData , Address , WriteData , MemoryRead , MemoryWrite , Clock);
    input [63:0]      WriteData;
    input [63:0]      Address;
    input             Clock, MemoryRead, MemoryWrite;
    output reg [63:0] ReadData;

    reg [7:0]         memBank [`SIZE-1:0];


    // This task is used to write arbitrary data to the Data Memory by
    // the intialization block.
    task initset;
      input [63:0] addr;
      input [63:0] data;
      begin
     memBank[addr] =  data[63:56] ; // Big-endian for the win...
     memBank[addr+1] =  data[55:48];
     memBank[addr+2] =  data[47:40];
     memBank[addr+3] =  data[39:32];
     memBank[addr+4] =  data[31:24];
     memBank[addr+5] =  data[23:16];
     memBank[addr+6] =  data[15:8];
     memBank[addr+7] =  data[7:0];
      end
    endtask


    initial
    begin
        // preseting some data in the data memory used by test #1

        // Address 0x0 gets 0x1
        initset( 64'h0,  64'h1);  //Counter variable
        initset( 64'h8,  64'ha);  //Part of mask
        initset( 64'h10, 64'h5);  //Other part of mask
        initset( 64'h18, 64'h0ffbea7deadbeeff); //big constant
        initset( 64'h20, 64'h0); //clearing space

        // Add any data you need for your tests here.

    end

    // This always block reads the data memory and places a double word
    // on the ReadData bus.
    always @(posedge Clock)
    begin
        if(MemoryRead)
        begin
            ReadData[63:56] <= #20 memBank[Address];
            ReadData[55:48] <= #20 memBank[Address+1];
            ReadData[47:40] <= #20 memBank[Address+2];
            ReadData[39:32] <= #20 memBank[Address+3];
            ReadData[31:24] <= #20 memBank[Address+4];
            ReadData[23:16] <= #20 memBank[Address+5];
            ReadData[15:8] <= #20 memBank[Address+6];
            ReadData[7:0] <= #20 memBank[Address+7];
        end
    end

    // This always block takes data from the WriteData bus and writes
    // it into the DataMemory.
    always @(posedge Clock)
    begin
        if(MemoryWrite)
        begin
            memBank[Address] <= #20 WriteData[63:56] ;
            memBank[Address+1] <= #20 WriteData[55:48];
            memBank[Address+2] <= #20 WriteData[47:40];
            memBank[Address+3] <= #20 WriteData[39:32];
            memBank[Address+4] <= #20 WriteData[31:24];
            memBank[Address+5] <= #20 WriteData[23:16];
            memBank[Address+6] <= #20 WriteData[15:8];
            memBank[Address+7] <= #20 WriteData[7:0];
            // Could be useful for debugging:
            // $display("Writing Address:%h Data:%h",Address, WriteData);
        end
    end
endmodule

Computer Architecture and Design/Lab 8/ALU.v
`define AND   4'b0000
`define OR    4'b0001
`define ADD   4'b0010
`define SUB   4'b0110
`define PassB 4'b0111

module ALU(BusW, BusA, BusB, ALUCtrl, Zero);
    
    parameter n = 64;

    output  [n-1:0] BusW;
    input   [n-1:0] BusA, BusB;
    input   [3:0] ALUCtrl;
    output  Zero;
    
    reg     [n-1:0] BusW;
    
    always @(ALUCtrl or BusA or BusB) begin
        case(ALUCtrl)
            `AND: begin
                BusW <= #20 BusA & BusB;
            end
            `OR: begin
                BusW <= #20 BusA | BusB;
            end
            `ADD: begin
                BusW <= #20 BusA + BusB;
            end
            `SUB: begin
                BusW <= #20 BusA - BusB;
            end
            `PassB: begin
                BusW <= #20  BusB;
            end
            
        endcase
    end

    assign #1 Zero = (BusW ? 1'b0 : 1'b1);
endmodule

Computer Architecture and Design/Lab 8/SignExtender.v


module SignExtender(out, inst, Ctrl); 
  output reg signed  [63:0] out; 
  input wire [31:0] inst; 
  input wire [2:0] Ctrl; 
  //reg 

  always @* begin
      case ( Ctrl )
        0 : begin
          out = {52'b0,inst[21:10]}; //I
        end
        1 : begin
          out = {{55{inst[20]}},inst[20:12]}; //D
        end
        2 : begin
           out = {{36{inst[25]}},inst[25:0],2'b0}; //B
        end
        3 : begin
          out = {{43{inst[23]}},inst[23:5],2'b0}; //CBZ
        end
        
        4: begin
          case(inst[22:21])
            0: begin
                out = {48'b0,inst[20:5]};
            end
            1:begin
                out = {32'b0,inst[20:5],16'b0};
            end
            
            2: begin
                out = {16'b0,inst[20:5],32'b0};
            end
            
            3: begin
                out = {inst[20:5],48'b0};
            end
            endcase
            end
        
        
          
          //,inst[20:5],{{16*{inst[22:21]}}{1'b0}}};
  endcase
  
  
  end
  
    //assign out = {36{inst[25]},inst[25:0],2'b0};
  
    
        
  
    //assign #1 extBit = (Ctrl ? 1'b0 : Imm16[15]); 
    //assign BusImm = {{16{extBit}}, Imm16}; 
  //initial
    //begin
        //$monitor("out=%b, outd = %d, b = %b",out,out, inst);
   // end

endmodule

Computer Architecture and Design/Lab 8/NextPClogic.v

module NextPClogic(NextPC, CurrentPC, SignExtImm64, Branch, ALUZero, Uncondbranch);
       input wire [63:0] CurrentPC, SignExtImm64;
       input wire Branch, ALUZero, Uncondbranch;
       output reg [63:0] NextPC;
       reg [63:0] ALUResult ;
       reg [63:0] AddFour;
       //reg PostMux;
       reg AndBranchZero;
       reg selector;
       always @(*) begin //everthing in the always loop runs when anything changes
        ALUResult <= #2 SignExtImm64 + CurrentPC; //adds offset to PC
        AddFour <= #1 CurrentPC + 4; //increment pc by 4
        
        AndBranchZero <= Branch & ALUZero; //for CBZ
        selector <= AndBranchZero | Uncondbranch; //if B, then add offset to pc no matter what
        if (selector) //mux logic
            NextPC <= #1 ALUResult;
        else
            NextPC <= #1 AddFour;
      end
      
       /*initial
    begin
        $monitor("currentPC=%d, NextPC = %d, AndBranchZero = %d, ALUResult = %d, AddFour = %d, ALUZero = %d",CurrentPC,NextPC,AndBranchZero,ALUResult, AddFour, ALUZero);
    end*/

endmodule

Computer Architecture and Design/Lab 8/RegisterFile.v

module RegisterFile(BusA, BusB, BusW,RA, RB, RW, RegWr, Clk);
    output wire [63:0] BusA;
    output wire  [63:0] BusB;
    input wire [63:0] BusW;
    input wire [4:0] RA;
    input wire [4:0] RB;
    input wire [4:0] RW;
    input wire RegWr;
    input wire Clk;
    reg [63:0] registers [31:0];
    
    //assign
    //X31 always needs to be XZR so it sets itself to zero at Clk (for the
    //beginning) and whenever it is changed. 
    always @ (Clk or registers[31]) begin 
        registers[31] <= 64'd0; 
    end
    //BusA and BusB assigned immediately
       assign  #2 BusA = registers[RA];
       assign  #2 BusB = registers[RB];
    //end
     
    //register write only happens on negedge when RegWr is 1
    always @ (negedge Clk) begin
        if(RegWr)
            registers[RW] <= #3 BusW;
    end
    
    /*initial
        begin
            $monitor("x9=%h, x10 = %h, x11 = %d, x12 = %d, x13 = %d",registers[9],registers[10],registers[11],registers[12], registers[13]);
        end*/
endmodule

Computer Architecture and Design/Lab 8/control.v
`define OPCODE_ANDREG 11'b?0001010???
`define OPCODE_ORRREG 11'b?0101010???
`define OPCODE_ADDREG 11'b?0?01011???
`define OPCODE_SUBREG 11'b?1?01011???

`define OPCODE_ADDIMM 11'b?0?10001???
`define OPCODE_SUBIMM 11'b?1?10001???

`define OPCODE_MOVZ   11'b110100101??

`define OPCODE_B      11'b?00101?????
`define OPCODE_CBZ    11'b?011010????

`define OPCODE_LDUR   11'b??111000010
`define OPCODE_STUR   11'b??111000000

module control(
    output reg reg2loc,
    output reg alusrc,
    output reg mem2reg,
    output reg regwrite,
    output reg memread,
    output reg memwrite,
    output reg branch,
    output reg uncond_branch,
    output reg [3:0] aluop,
    output reg [2:0] signop,
    input [10:0] opcode
);

always @(*)
begin
    casez (opcode)
        
        `OPCODE_ANDREG: begin
            reg2loc       <= 1'b0;
            alusrc        <= 1'b0;
            mem2reg       <= 1'b0;
            regwrite      <= 1'b1;
            memread       <= 1'b0;
            memwrite      <= 1'b0;
            branch        <= 1'b0;
            uncond_branch <= 1'b0;
            aluop         <= 4'b0000;
            signop        <= 3'bxx;
        end

        `OPCODE_ORRREG: begin
            reg2loc       <= 1'b0;
            alusrc        <= 1'b0;
            mem2reg       <= 1'b0;
            regwrite      <= 1'b1;
            memread       <= 1'b0;
            memwrite      <= 1'b0;
            branch        <= 1'b0;
            uncond_branch <= 1'b0;
            aluop         <= 4'b0001;
            signop        <= 3'bxx;
        end

        `OPCODE_ADDREG: begin
            reg2loc       <= 1'b0;
            alusrc        <= 1'b0;
            mem2reg       <= 1'b0;
            regwrite      <= 1'b1;
            memread       <= 1'b0;
            memwrite      <= 1'b0;
            branch        <= 1'b0;
            uncond_branch <= 1'b0;
            aluop         <= 4'b0010;
            signop        <= 3'bxx;
        end

         `OPCODE_SUBREG: begin
            reg2loc       <= 1'b0;
            alusrc        <= 1'b0;
            mem2reg       <= 1'b0;
            regwrite      <= 1'b1;
            memread       <= 1'b0;
            memwrite      <= 1'b0;
            branch        <= 1'b0;
            uncond_branch <= 1'b0;
            aluop         <= 4'b0110;
            signop        <= 3'bxx;
        end

         `OPCODE_ADDIMM: begin
            reg2loc       <= 1'b0;
            alusrc        <= 1'b1;
            mem2reg       <= 1'b0;
            regwrite      <= 1'b1;
            memread       <= 1'b0;
            memwrite      <= 1'b0;
            branch        <= 1'b0;
            uncond_branch <= 1'b0;
            aluop         <= 4'b0010;
            signop        <= 3'b00;
        end

        `OPCODE_SUBIMM: begin
            reg2loc       <= 1'b0;
            alusrc        <= 1'b1;
            mem2reg       <= 1'b0;
            regwrite      <= 1'b1;
            memread       <= 1'b0;
            memwrite      <= 1'b0;
            branch        <= 1'b0;
            uncond_branch <= 1'b0;
            aluop         <= 4'b0110;
            signop        <= 3'b00;
        end

        `OPCODE_B: begin
            reg2loc       <= 1'bx;
            alusrc        <= 1'bx;
            mem2reg       <= 1'bx;
            regwrite      <= 1'b0;
            memread       <= 1'b0;
            memwrite      <= 1'b0;
            branch        <= 1'bx;
            uncond_branch <= 1'b1;
            aluop         <= 4'bxxxx;
            signop        <= 3'b10;
        end

         `OPCODE_CBZ: begin
            reg2loc       <= 1'b1;
            alusrc        <= 1'b0;
            mem2reg       <= 1'bx;
            regwrite      <= 1'b0;
            memread       <= 1'b0;
            memwrite      <= 1'b0;
            branch        <= 1'b1;
            uncond_branch <= 1'b0;
            aluop         <= 4'b0111;
            signop        <= 3'b11;
        end

        `OPCODE_LDUR: begin
            reg2loc       <= 1'bx;
            alusrc        <= 1'b1;
            mem2reg       <= 1'b1;
            regwrite      <= 1'b1;
            memread       <= 1'b1;
            memwrite      <= 1'b0;
            branch        <= 1'b0;
            uncond_branch <= 1'b0;
            aluop         <= 4'b0010;
            signop        <= 3'b01;

        end

        `OPCODE_STUR: begin
            reg2loc       <= 1'b1;
            alusrc        <= 1'b1;
            mem2reg       <= 1'bx;
            regwrite      <= 1'b0;
            memread       <= 1'b0;
            memwrite      <= 1'b1;
            branch        <= 1'b0;
            uncond_branch <= 1'b0;
            aluop         <= 4'b0010;
            signop        <= 3'b01;

        end
        
        `OPCODE_MOVZ: begin
            reg2loc       <= 1'bx;
            alusrc        <= 1'b1;
            mem2reg       <= 1'b0;
            regwrite      <= 1'b1;
            memread       <= 1'b0;
            memwrite      <= 1'b0;
            branch        <= 1'b0;
            uncond_branch <= 1'b0;
            aluop         <= 4'b0111;
            signop        <= 3'b100;

        end

        default:
        begin
            reg2loc       <= 1'bx;
            alusrc        <= 1'bx;
            mem2reg       <= 1'bx;
            regwrite      <= 1'b0;
            memread       <= 1'b0;
            memwrite      <= 1'b0;
            branch        <= 1'b0;
            uncond_branch <= 1'b0;
            aluop         <= 4'bxxxx;
            signop        <= 3'bxx;
        end
    endcase
end

endmodule

Computer Architecture and Design/Lab 8/InstructionMemory.v



module InstructionMemory(Data, Address);
   parameter T_rd = 20;
   parameter MemSize = 40;
   
   output [31:0] Data;
   input [63:0]  Address;
   reg [31:0] 	 Data;
   
   /*
    * ECEN 350 Processor Test Functions
    * Texas A&M University
    */
   
   always @ (Address) begin
      #4;
      case(Address)

	/* Test Program 1:
	 * Program loads constants from the data memory. Uses these constants to test
	 * the following instructions: LDUR, ORR, AND, CBZ, ADD, SUB, STUR and B.
	 * 
	 * Assembly code for test:
	 * 
	 * 0: LDUR X9, [XZR, 0x0]    //Load 1 into x9
	 * 4: LDUR X10, [XZR, 0x8]   //Load a into x10
	 * 8: LDUR X11, [XZR, 0x10]  //Load 5 into x11
	 * C: LDUR X12, [XZR, 0x18]  //Load big constant into x12
	 * 10: LDUR X13, [XZR, 0x20]  //load a 0 into X13
	 * 
	 * 14: ORR X10, X10, X11  //Create mask of 0xf
	 * 18: AND X12, X12, X10  //Mask off low order bits of big constant
	 * 
	 * loop:
	 * 1C: CBZ X12, end  //while X12 is not 0
	 * 20: ADD X13, X13, X9  //Increment counter in X13
	 * 24: SUB X12, X12, X9  //Decrement remainder of big constant in X12
	 * 28: B loop  //Repeat till X12 is 0
	 * 2C: STUR X13, [XZR, 0x20]  //store back the counter value into the memory location 0x20
	 */
	

	63'h000: Data = 32'hF84003E9;
	63'h004: Data = 32'hF84083EA;
	63'h008: Data = 32'hF84103EB;
	63'h00c: Data = 32'hF84183EC;
	63'h010: Data = 32'hF84203ED;
	63'h014: Data = 32'hAA0B014A;
	63'h018: Data = 32'h8A0A018C;
	63'h01c: Data = 32'hB400008C;
	63'h020: Data = 32'h8B0901AD;
	63'h024: Data = 32'hCB09018C;
	63'h028: Data = 32'h17FFFFFD;
	63'h02c: Data = 32'hF80203ED;
	63'h030: Data = 32'hF84203ED;  //One last load to place stored value on memdbus for test checking.

	/* Add code for your tests here */
	
	//movz first quadrant to x10, add that with xzr to x9
	//movz second quadrant to x10, add that with x9 to x9
	// do same as previous step for next two quadrants
	
	63'h034: Data = {9'b110100101,2'd0,16'hdef0,5'd10};
	63'h038: Data = {11'b10001011000,5'd31,6'd0,5'd10,5'd9};
	63'h03c: Data = {9'b110100101,2'd1,16'h9abc,5'd10};
	63'h040: Data = {11'b10001011000,5'd9,6'd0,5'd10,5'd9};
	63'h044: Data = {9'b110100101,2'd2,16'h5678,5'd10};
	63'h048: Data = {11'b10001011000,5'd9,6'd0,5'd10,5'd9};
	63'h04c: Data = {9'b110100101,2'd3,16'h1234,5'd10};
	63'h050: Data = {11'b10001011000,5'd9,6'd0,5'd10,5'd9};
	
	//store
	63'h054: Data = {11'b11111000000,9'h28,2'd0,5'd31,5'd9};
	
	//load
	63'h058: Data = {11'b11111000010,9'h28,2'd0,5'd31,5'd10};
	


			
	default: Data = 32'hXXXXXXXX;
      endcase
   end
endmodule

Computer Architecture and Design/Lab 8/singlecycle.v
`include "ALU.v"
`include "InstructionMemory.v"
`include "control.v"
`include "RegisterFile.v"
`include "DataMemory.v"
`include "NextPClogic.v"
`include "SignExtender.v"

module singlecycle(
    input resetl,
    input [63:0] startpc,
    output reg [63:0] currentpc,
    output [63:0] dmemout,
    input CLK
);

    // Next PC connections
    wire [63:0] nextpc;       // The next PC, to be updated on clock cycle

    // Instruction Memory connections
    wire [31:0] instruction;  // The current instruction

    // Parts of instruction
    wire [4:0] rd;            // The destination register
    wire [4:0] rm;            // Operand 1
    wire [4:0] rn;            // Operand 2
    wire [10:0] opcode;
     wire [63:0] aluB;
     wire [63:0] writeData;

    // Control wires
    wire reg2loc;
    wire alusrc;
    wire mem2reg;
    wire regwrite;
    wire memread;
    wire memwrite;
    wire branch;
    wire uncond_branch;
    wire [3:0] aluctrl;
    wire [2:0] signop;

    // Register file connections
    wire [63:0] regoutA;     // Output A
    wire [63:0] regoutB;     // Output B

    // ALU connections
    wire [63:0] aluout;
    wire zero;

    // Sign Extender connections
    wire [63:0] extimm;

    // PC update logic
    always @(negedge CLK)
    begin
        if (resetl)
            currentpc <= nextpc;
        else
            currentpc <= startpc;
    end

    // Parts of instruction
    assign rd = instruction[4:0];
    assign rm = instruction[9:5];
    assign rn = reg2loc ? instruction[4:0] : instruction[20:16];
    assign opcode = instruction[31:21];
    assign aluB = alusrc ? extimm : regoutB;
    assign writeData = mem2reg ? dmemout : aluout;

    InstructionMemory imem(
        .Data(instruction),
        .Address(currentpc)
    );

    control control(
        .reg2loc(reg2loc),
        .alusrc(alusrc),
        .mem2reg(mem2reg),
        .regwrite(regwrite),
        .memread(memread),
        .memwrite(memwrite),
        .branch(branch),
        .uncond_branch(uncond_branch),
        .aluop(aluctrl),
        .signop(signop),
        .opcode(opcode)
    );
    
    RegisterFile regFile(
        .BusA(regoutA),
        .BusB(regoutB),
        .BusW(writeData),
        .RA(rm),
        .RB(rn),
        .RW(rd),
        .RegWr(regwrite),
        .Clk(CLK)
        
    );
    
    NextPClogic NPC(
        .NextPC(nextpc),
        .CurrentPC(currentpc),
        .SignExtImm64(extimm),
        .Branch(branch),
        .ALUZero(zero),
        .Uncondbranch(uncond_branch)
        
    
    );
    
    SignExtender SignEx(
        .out(extimm),
        .inst(instruction),
        .Ctrl(signop)
    
    );
    
    ALU alu (
        .BusW(aluout),
        .BusA(regoutA),
        .BusB(aluB),
        .ALUCtrl(aluctrl),
        .Zero(zero)
    
    );
    
    DataMemory DM (
        .ReadData(dmemout),
        .Address(aluout),
        .WriteData(regoutB),
        .MemoryRead(memread),
        .MemoryWrite(memwrite),
        .Clock(CLK)
    
    );
    
    
    
    

    /*
    * Connect the remaining datapath elements below.
    * Do not forget any additional multiplexers that may be required.
    */



endmodule

Computer Architecture and Design/Lab 8/SingleCycleProcTest.v
`timescale 1ns / 1ps

`define STRLEN 32
`define HalfClockPeriod 60
`define ClockPeriod `HalfClockPeriod * 2

module SingleCycleProcTest_v;

    initial
    begin
        $dumpfile("singlecycle.vcd");
        $dumpvars;
    end

    // These tasks are used to check if a given test has passed and
    // confirm that all tests passed.
    task passTest;
        input [63:0] actualOut, expectedOut;
        input [`STRLEN*8:0] testType;
        inout [7:0] 	  passed;

        if(actualOut == expectedOut) begin $display ("%s passed", testType); passed = passed + 1; end
        else $display ("%s failed: 0x%x should be 0x%x", testType, actualOut, expectedOut);
    endtask

    task allPassed;
        input [7:0] passed;
        input [7:0] numTests;

        if(passed == numTests) $display ("All tests passed");
        else $display("Some tests failed: %d of %d passed", passed, numTests);
    endtask

    // Inputs
    reg        CLK;
    reg        Reset_L;
    reg [63:0] startPC;
    reg [7:0]  passed;
    reg [15:0] watchdog;

    // Outputs
    wire [63:0] dMemOut;
    wire [63:0] currentPC;

    // Instantiate the Unit Under Test (UUT)
    singlecycle uut (
        .CLK(CLK),
        .resetl(Reset_L),
        .startpc(startPC),
        .currentpc(currentPC),
        .dmemout(dMemOut)
    );

    initial begin
        // Initialize Inputs
        Reset_L = 1;
        startPC = 0;
        passed = 0;

        // Initialize Watchdog timer
        watchdog = 0;

        // Wait for global reset
        #(1 * `ClockPeriod);

        // Program 1
        #1
        Reset_L = 0; startPC = 0;
        #(1 * `ClockPeriod);
        Reset_L = 1;

        // ***********************************************************
        // This while loop will continue cycling the processor until the
        // PC reaches the final instruction in the first test.  If the
        // program forms an infinite loop, never reaching the end, the
        // watchdog timer will kick in and kill simulation after 64K
        // cycles.
        // ***********************************************************

        while (currentPC < 64'h34)
        begin
           #(1 * `ClockPeriod);
           $display("CurrentPC:%h",currentPC);
        end
        #(1 * `ClockPeriod);	// One more cycle to load the pass code from the DataMemory.
        passTest(dMemOut, 64'hF, "Results of Program 1", passed);
        
        while (currentPC < 64'h5c)
        begin
           #(1 * `ClockPeriod);
           $display("CurrentPC:%h",currentPC);
        end
        #(1 * `ClockPeriod);	// One more cycle to load the pass code from the DataMemory.
        passTest(dMemOut, 64'h123456789abcdef0, "Results of Program 2", passed);

        // ***********************************************************
        // Add your new tests here
        // ***********************************************************

        // Done
        allPassed(passed, 2);   // Be sure to change the one to match
                                // the number of tests you add.
        $finish;
    end

    initial begin
        CLK = 0;
    end

    // The following is correct if clock starts at LOW level at StartTime //
    always begin
        #`HalfClockPeriod CLK = ~CLK;
        #`HalfClockPeriod CLK = ~CLK;
        watchdog = watchdog +1;
    end

    // Kill the simulation if the watchdog hits 64K cycles
    always @*
        if (watchdog == 16'hFF)
        begin
            $display("Watchdog Timer Expired.");
            $finish;
        end


endmodule

Computer Architecture and Design/Lab 8/singlecycle.vcd
$date
	Thu Apr 29 22:21:16 2021
$end
$version
	Icarus Verilog
$end
$timescale
	1ps
$end
$scope module SingleCycleProcTest_v $end
$var wire 64 ! dMemOut [63:0] $end
$var wire 64 " currentPC [63:0] $end
$var reg 1 # CLK $end
$var reg 1 $ Reset_L $end
$var reg 8 % passed [7:0] $end
$var reg 64 & startPC [63:0] $end
$var reg 16 ' watchdog [15:0] $end
$scope module uut $end
$var wire 1 # CLK $end
$var wire 1 $ resetl $end
$var wire 64 ( startpc [63:0] $end
$var wire 1 ) zero $end
$var wire 64 * writeData [63:0] $end
$var wire 1 + uncond_branch $end
$var wire 3 , signop [2:0] $end
$var wire 5 - rn [4:0] $end
$var wire 5 . rm [4:0] $end
$var wire 1 / regwrite $end
$var wire 64 0 regoutB [63:0] $end
$var wire 64 1 regoutA [63:0] $end
$var wire 1 2 reg2loc $end
$var wire 5 3 rd [4:0] $end
$var wire 11 4 opcode [10:0] $end
$var wire 64 5 nextpc [63:0] $end
$var wire 1 6 memwrite $end
$var wire 1 7 memread $end
$var wire 1 8 mem2reg $end
$var wire 32 9 instruction [31:0] $end
$var wire 64 : extimm [63:0] $end
$var wire 64 ; dmemout [63:0] $end
$var wire 1 < branch $end
$var wire 1 = alusrc $end
$var wire 64 > aluout [63:0] $end
$var wire 4 ? aluctrl [3:0] $end
$var wire 64 @ aluB [63:0] $end
$var reg 64 A currentpc [63:0] $end
$scope module DM $end
$var wire 1 # Clock $end
$var wire 64 B WriteData [63:0] $end
$var wire 1 6 MemoryWrite $end
$var wire 1 7 MemoryRead $end
$var wire 64 C Address [63:0] $end
$var reg 64 D ReadData [63:0] $end
$scope task initset $end
$var reg 64 E addr [63:0] $end
$var reg 64 F data [63:0] $end
$upscope $end
$upscope $end
$scope module NPC $end
$var wire 64 G CurrentPC [63:0] $end
$var wire 1 + Uncondbranch $end
$var wire 64 H SignExtImm64 [63:0] $end
$var wire 1 < Branch $end
$var wire 1 ) ALUZero $end
$var reg 64 I ALUResult [63:0] $end
$var reg 64 J AddFour [63:0] $end
$var reg 1 K AndBranchZero $end
$var reg 64 L NextPC [63:0] $end
$var reg 1 M selector $end
$upscope $end
$scope module SignEx $end
$var wire 32 N inst [31:0] $end
$var wire 3 O Ctrl [2:0] $end
$var reg 64 P out [63:0] $end
$upscope $end
$scope module alu $end
$var wire 64 Q BusB [63:0] $end
$var wire 1 ) Zero $end
$var wire 64 R BusA [63:0] $end
$var wire 4 S ALUCtrl [3:0] $end
$var reg 64 T BusW [63:0] $end
$upscope $end
$scope module control $end
$var wire 11 U opcode [10:0] $end
$var reg 4 V aluop [3:0] $end
$var reg 1 = alusrc $end
$var reg 1 < branch $end
$var reg 1 8 mem2reg $end
$var reg 1 7 memread $end
$var reg 1 6 memwrite $end
$var reg 1 2 reg2loc $end
$var reg 1 / regwrite $end
$var reg 3 W signop [2:0] $end
$var reg 1 + uncond_branch $end
$upscope $end
$scope module imem $end
$var wire 64 X Address [63:0] $end
$var reg 32 Y Data [31:0] $end
$upscope $end
$scope module regFile $end
$var wire 64 Z BusA [63:0] $end
$var wire 64 [ BusB [63:0] $end
$var wire 64 \ BusW [63:0] $end
$var wire 1 # Clk $end
$var wire 5 ] RA [4:0] $end
$var wire 5 ^ RB [4:0] $end
$var wire 5 _ RW [4:0] $end
$var wire 1 / RegWr $end
$upscope $end
$upscope $end
$scope task allPassed $end
$var reg 8 ` numTests [7:0] $end
$var reg 8 a passed [7:0] $end
$upscope $end
$scope task passTest $end
$var reg 64 b actualOut [63:0] $end
$var reg 64 c expectedOut [63:0] $end
$var reg 8 d passed [7:0] $end
$var reg 257 e testType [256:0] $end
$upscope $end
$upscope $end
$enddefinitions $end
#0
$dumpvars
bx e
bx d
bx c
bx b
bx a
bx `
bx _
bx ^
bx ]
bx \
bx [
bx Z
bx Y
bx X
bx W
bx V
bx U
bx T
bx S
bx R
bx Q
bx P
bx O
bx N
xM
bx L
xK
bx J
bx I
bx H
bx G
b0 F
b100000 E
bx D
bx C
bx B
bx A
bx @
bx ?
bx >
x=
x<
bx ;
bx :
bx 9
x8
x7
x6
bx 5
bx 4
bx 3
x2
bx 1
bx 0
x/
bx .
bx -
bx ,
x+
bx *
x)
b0 (
b0 '
b0 &
b0 %
1$
0#
bx "
bx !
$end
#60000
1#
#120000
b1 '
0#
#121000
0$
#180000
1#
#240000
b0 "
b0 A
b0 G
b0 X
b10 '
0#
#241000
b100 J
1$
#242000
b100 5
b100 L
#244000
0M
0K
b0 @
b0 Q
b0 :
b0 H
b0 P
b1 ,
b1 O
b1 W
b10 ?
b10 S
b10 V
0+
0<
06
17
1/
18
1=
b0x00x -
b0x00x ^
b11111000010 4
b11111000010 U
b11111 .
b11111 ]
b1001 3
b1001 _
b11111000010000000000001111101001 9
b11111000010000000000001111101001 N
b11111000010000000000001111101001 Y
#246000
b0 I
b0 1
b0 R
b0 Z
#266000
b0 >
b0 C
b0 T
#267000
1)
#300000
1#
#320000
b1 *
b1 \
b1 !
b1 ;
b1 D
#360000
b100 "
b100 A
b100 G
b100 X
b11 '
0#
#361000
b1000 J
#362000
b1000 5
b1000 L
b100 I
#364000
b0x0x0 -
b0x0x0 ^
b1000 @
b1000 Q
b1010 3
b1010 _
b1000 :
b1000 H
b1000 P
b11111000010000001000001111101010 9
b11111000010000001000001111101010 N
b11111000010000001000001111101010 Y
#366000
b1100 I
#384000
b1000 >
b1000 C
b1000 T
#385000
0)
#420000
1#
#440000
b1010 *
b1010 \
b1010 !
b1010 ;
b1010 D
#480000
b1000 "
b1000 A
b1000 G
b1000 X
b100 '
0#
#481000
b1100 J
#482000
b1100 5
b1100 L
b10000 I
#484000
b0x0x1 -
b0x0x1 ^
b10000 @
b10000 Q
b1011 3
b1011 _
b10000 :
b10000 H
b10000 P
b11111000010000010000001111101011 9
b11111000010000010000001111101011 N
b11111000010000010000001111101011 Y
#486000
b11000 I
#504000
b10000 >
b10000 C
b10000 T
#540000
1#
#560000
b101 *
b101 \
b101 !
b101 ;
b101 D
#600000
b1100 "
b1100 A
b1100 G
b1100 X
b101 '
0#
#601000
b10000 J
#602000
b10000 5
b10000 L
b11100 I
#604000
b0xx0x -
b0xx0x ^
b11000 @
b11000 Q
b1100 3
b1100 _
b11000 :
b11000 H
b11000 P
b11111000010000011000001111101100 9
b11111000010000011000001111101100 N
b11111000010000011000001111101100 Y
#606000
b100100 I
#624000
b11000 >
b11000 C
b11000 T
#660000
1#
#680000
b111111111011111010100111110111101010110110111110111011111111 *
b111111111011111010100111110111101010110110111110111011111111 \
b111111111011111010100111110111101010110110111110111011111111 !
b111111111011111010100111110111101010110110111110111011111111 ;
b111111111011111010100111110111101010110110111110111011111111 D
#720000
b10000 "
b10000 A
b10000 G
b10000 X
b110 '
0#
#721000
b10100 J
#722000
b10100 5
b10100 L
b101000 I
#724000
b0xxxx -
b0xxxx ^
b100000 @
b100000 Q
b1101 3
b1101 _
b100000 :
b100000 H
b100000 P
b11111000010000100000001111101101 9
b11111000010000100000001111101101 N
b11111000010000100000001111101101 Y
#726000
b110000 I
#744000
b100000 >
b100000 C
b100000 T
#780000
1#
#800000
b0 *
b0 \
b0 !
b0 ;
b0 D
#840000
b10100 "
b10100 A
b10100 G
b10100 X
b111 '
0#
#841000
b11000 J
#842000
b11000 5
b11000 L
b110100 I
#844000
b100000 *
b100000 \
bx ,
bx O
bx W
b1 ?
b1 S
b1 V
07
08
0=
02
b1011 -
b1011 ^
bx @
bx Q
b10101010000 4
b10101010000 U
b1010 .
b1010 ]
b1010 3
b1010 _
b10110000 :
b10110000 H
b10110000 P
b10101010000010110000000101001010 9
b10101010000010110000000101001010 N
b10101010000010110000000101001010 Y
#846000
b11000100 I
b101 @
b101 Q
b101 0
b101 B
b101 [
b1010 1
b1010 R
b1010 Z
#864000
bx *
bx \
bx >
bx C
bx T
#865000
x)
#866000
b1111 *
b1111 \
b1111 >
b1111 C
b1111 T
#867000
0)
#900000
1#
#960000
b11000 "
b11000 A
b11000 G
b11000 X
b1000 '
0#
#961000
b11100 J
#962000
b11100 5
b11100 L
b11001000 I
#964000
b0 ?
b0 S
b0 V
b1010 -
b1010 ^
b10001010000 4
b10001010000 U
b1100 .
b1100 ]
b1100 3
b1100 _
b10001010000010100000000110001100 9
b10001010000010100000000110001100 N
b10001010000010100000000110001100 Y
#966000
b1111 @
b1111 Q
b1111 0
b1111 B
b1111 [
b111111111011111010100111110111101010110110111110111011111111 1
b111111111011111010100111110111101010110110111110111011111111 R
b111111111011111010100111110111101010110110111110111011111111 Z
#984000
b0 *
b0 \
b0 >
b0 C
b0 T
#985000
1)
#986000
b1111 *
b1111 \
b1111 >
b1111 C
b1111 T
#987000
0)
#1020000
1#
#1080000
b11100 "
b11100 A
b11100 G
b11100 X
b1001 '
0#
#1081000
b100000 J
#1082000
b100000 5
b100000 L
b11001100 I
#1084000
b10000 :
b10000 H
b10000 P
b0xxxx *
b0xxxx \
b11 ,
b11 O
b11 W
b111 ?
b111 S
b111 V
1<
0/
x8
12
b1100 -
b1100 ^
b10110100000 4
b10110100000 U
b100 .
b100 ]
b10110100000000000000000010001100 9
b10110100000000000000000010001100 N
b10110100000000000000000010001100 Y
#1086000
b101100 I
bx 1
bx R
bx Z
#1140000
1#
#1200000
b100000 "
b100000 A
b100000 G
b100000 X
b1010 '
0#
#1201000
b100100 J
#1202000
b100100 5
b100100 L
b110000 I
#1204000
b1111 *
b1111 \
bx ,
bx O
bx W
b10 ?
b10 S
b10 V
0<
1/
08
02
b1001 -
b1001 ^
b10001011000 4
b10001011000 U
b1101 .
b1101 ]
b1101 3
b1101 _
b10010000000110100 :
b10010000000110100 H
b10010000000110100 P
b10001011000010010000000110101101 9
b10001011000010010000000110101101 N
b10001011000010010000000110101101 Y
#1206000
b10010000001010100 I
b1 @
b1 Q
b1 0
b1 B
b1 [
b0 1
b0 R
b0 Z
#1224000
bx *
bx \
bx >
bx C
bx T
#1225000
x)
#1226000
b1 *
b1 \
b1 >
b1 C
b1 T
#1227000
0)
#1260000
1#
